<?xml version="1.0" encoding="UTF-8"?>
<rccOrigemDeContato>
    <locate>origemdecontatoid</locate>
    <ignoreOnUpdate>descricao</ignoreOnUpdate>
    
    <item>
        <descricao>Ouvidoria</descricao>
        <origemdecontatoid>1</origemdecontatoid>
    </item>
    <item>
        <descricao>Telefone</descricao>
        <origemdecontatoid>2</origemdecontatoid>
    </item>
    <item>
        <descricao>Email</descricao>
        <origemdecontatoid>3</origemdecontatoid>
    </item>
    <item>
        <descricao>Carta</descricao>
        <origemdecontatoid>4</origemdecontatoid>
    </item>
</rccOrigemDeContato>
