<?xml version="1.0" encoding="ISO-8859-1" standalone="yes"?> 
<map>
	<moduleName>admin</moduleName>
	<className>log</className>
	<tableName>miolo_log</tableName>
	<databaseName>miolo</databaseName>
	<attribute>
		<attributeName>idlog</attributeName>
		<columnName>idlog</columnName>
		<key>primary</key>
                <idgenerator>seq_miolo_log</idgenerator>
        </attribute>
	<attribute>
		<attributeName>m_timestamp</attributeName>
		<columnName>m_timestamp</columnName>
	</attribute>
	<attribute>
		<attributeName>description</attributeName>
		<columnName>description</columnName>
	</attribute>
        <attribute>
		<attributeName>module</attributeName>
		<columnName>module</columnName>
	</attribute>
	<attribute>
		<attributeName>class</attributeName>
		<columnName>class</columnName>
	</attribute>
	<attribute>
		<attributeName>iduser</attributeName>
		<columnName>iduser</columnName>
	</attribute>
	<attribute>
		<attributeName>idtransaction</attributeName>
		<columnName>idtransaction</columnName>
	</attribute>
</map>
