<?xml version="1.0" encoding="UTF-8"?>
<gtcholiday>
    <locate>holidayid</locate>
    <ignoreOnUpdate>*</ignoreOnUpdate>
        <item>
        <date><![CDATA[25/12/2008]]></date>
        <description>Natal</description>
        <holidayid>1</holidayid>
        <occursallyear>t</occursallyear>
    </item>
    <item>
        <date><![CDATA[01/05/2008]]></date>
        <description>Dia do Trabalho</description>
        <holidayid>2</holidayid>
        <occursallyear>t</occursallyear>
    </item>
    <item>
        <date><![CDATA[01/01/2008]]></date>
        <description>1ยบ Janeiro</description>
        <holidayid>3</holidayid>
        <occursallyear>t</occursallyear>
    </item>
</gtcholiday>
